babls.py
setup.py
babtools_tags.egg-info/PKG-INFO
babtools_tags.egg-info/SOURCES.txt
babtools_tags.egg-info/dependency_links.txt
babtools_tags.egg-info/top_level.txt